{"schema_version":"MB_AUTOMATION_STATUS_V2","status":"TRANSIENT_FAILURE_LAST_VALID_PLAN_PRESERVED","phase":"SOURCE_ACCESS","reason":"Không khóa được nguồn Google hoặc tối thiểu hai nguồn công khai. Giữ nguyên kế hoạch hợp lệ gần nhất; không thay website bằng A0 lỗi truy cập.","updated_at":"2026-07-12T22:43:57+07:00","website_payload_overwritten":false,"last_valid_report_run_id":"RPT_MB_20260713_PARALLEL_NEXT_ALL_METHODS","last_valid_target_date":"2026-07-13","last_valid_locked_through":"2026-07-12","last_valid_decision":"X2_CORE_EXACT","last_valid_milestones_complete":true,"retry_policy":"Keep data/current.json unchanged; retry at next scheduled run."}
