{
  "schema_version": "MB_FUSION4_180_WEB_V1",
  "audit_id": "MB-20260719-FUSION4-180",
  "generated_at": "2026-07-19T08:00:00+07:00",
  "timezone": "Asia/Bangkok",
  "method": {
    "short_name": "MB FUSION4–180",
    "official_name": "MB FUSION4–180",
    "config_id": "MB_FUSION4_180_PROD_V1_20260719",
    "status": "PRODUCTION_OFFICIAL",
    "locked_from": "2026-07-19",
    "ranking_formula": "0.75*Max4_rank + 0.25*Max10_priority_rank + 0.50*I(code_in_Max10)",
    "a1_role": "AUDIT_CONFIRMATION_ONLY_IN_FIXED_K4",
    "promotion_note": "Chỉ thay khi nhánh mới vượt kiểm định nhân quả và tiêu chí rủi ro đã khóa."
  },
  "plan": {
    "target_date": "2026-07-19",
    "data_lock_date": "2026-07-18",
    "status": "LOCKED_WAITING_RESULT",
    "method": "MB FUSION4–180",
    "config_id": "MB_FUSION4_180_PROD_V1_20260719",
    "codes": [
      "59",
      "78",
      "06",
      "10"
    ],
    "number_of_codes": 4,
    "ranked_points": [
      50,
      50,
      50,
      30
    ],
    "points_by_code": {
      "59": 50,
      "78": 50,
      "06": 50,
      "10": 30
    },
    "total_points": 180,
    "cost_per_point_vnd": 23000,
    "total_capital_vnd": 4140000,
    "maximum_loss_vnd": 4140000,
    "core_100_enabled": false,
    "other_50_enabled": false,
    "outcome_known_at_selection": false,
    "selection_input_hash": "68389431cc7d83540d3a3cf2d6cb62499abbb5e808bab0f811d56f1b90626c48"
  },
  "overlay": {
    "active": false,
    "eligible_width": false,
    "normalized_margin": 0,
    "activation_threshold": 1,
    "decision": "DISABLED_BY_FIXED_FUSION4"
  },
  "stake_policy": [
    {
      "rank_from": 1,
      "rank_to": 3,
      "points_per_code": 50
    },
    {
      "rank_from": 4,
      "rank_to": 4,
      "points_per_code": 30
    }
  ],
  "latest_settlement": {
    "date": "2026-07-18",
    "status": "BACKTEST_CAUSAL_REPLAY_27_OF_27",
    "ledger_scope": "METHOD_THEORETICAL_SEPARATE_FROM_PERSONAL_ACTUAL",
    "method": "MB FUSION4–180",
    "config_id": "MB_FUSION4_180_PROD_V1_20260719",
    "codes": [
      "57",
      "55",
      "91",
      "54"
    ],
    "points_by_code": {
      "57": 50,
      "55": 50,
      "91": 50,
      "54": 30
    },
    "total_points": 180,
    "hits_by_code": {
      "57": 0,
      "55": 0,
      "91": 0,
      "54": 1
    },
    "hit_codes": [
      "54"
    ],
    "hit_units": 1,
    "hit_day": true,
    "profit_day": false,
    "capital_vnd": 4140000,
    "payout_vnd": 2400000,
    "pnl_vnd": -1740000,
    "roi_pct": -42.028985507246375,
    "draw_hash": "f4cbafab52bbfd2701d34c9ea7852bbe3f78b6812fd3812c62366d0bf772204c"
  },
  "actual_performance": {
    "official_start_date": "2026-07-19",
    "settled_through": "2026-07-18",
    "current_month_id": "2026-07",
    "current_month": {
      "sessions": 0,
      "wins": 0,
      "losses": 0,
      "current_winning_streak": 0,
      "current_losing_streak": 0,
      "longest_winning_streak": 0,
      "longest_losing_streak": 0,
      "net_profit_vnd": 0
    },
    "total": {
      "sessions": 0,
      "wins": 0,
      "losses": 0,
      "current_winning_streak": 0,
      "current_losing_streak": 0,
      "longest_winning_streak": 0,
      "longest_losing_streak": 0,
      "net_profit_vnd": 0
    }
  },
  "backtest": {
    "current_month": {
      "sessions": 18,
      "hit_days": 16,
      "hit_day_rate_pct": 88.88888888888889,
      "profit_days": 9,
      "profit_day_rate_pct": 50.0,
      "capital_vnd": 74520000,
      "payout_vnd": 101600000,
      "net_profit_vnd": 27080000,
      "roi_pct": 36.33923778851315,
      "profit_factor": 2.926031294452347,
      "max_drawdown_vnd": -6020000,
      "longest_losing_streak": 3,
      "gross_profit_vnd": 41140000,
      "gross_loss_vnd": 14060000
    },
    "current_year": {
      "sessions": 195,
      "hit_days": 175,
      "hit_day_rate_pct": 89.74358974358975,
      "profit_days": 94,
      "profit_day_rate_pct": 48.205128205128204,
      "capital_vnd": 807300000,
      "payout_vnd": 1154400000,
      "net_profit_vnd": 347100000,
      "roi_pct": 42.99516908212561,
      "profit_factor": 3.86055711224658,
      "max_drawdown_vnd": -12700000,
      "longest_losing_streak": 5,
      "gross_profit_vnd": 468440000,
      "gross_loss_vnd": 121340000
    },
    "full": {
      "sessions": 918,
      "hit_days": 726,
      "hit_day_rate_pct": 79.08496732026144,
      "profit_days": 383,
      "profit_day_rate_pct": 41.72113289760348,
      "capital_vnd": 3800520000,
      "payout_vnd": 4745600000,
      "net_profit_vnd": 945080000,
      "roi_pct": 24.86712344626525,
      "profit_factor": 1.9623052642297119,
      "max_drawdown_vnd": -43040000,
      "longest_losing_streak": 12,
      "gross_profit_vnd": 1927180000,
      "gross_loss_vnd": 982100000
    }
  },
  "constraints": {
    "fixed_total_codes": 4,
    "maximum_total_points": 180,
    "duplicate_codes": 0,
    "martingale": false,
    "same_day_outcome_leakage": false,
    "personal_actual_pnl_is_separate": true
  },
  "audit": {
    "source_history_primary_equals_mirror": true,
    "source_history_date": "2026-07-18",
    "source_result_units": 27,
    "ranking_artifact_sha256": "b2c076c7bffdde97662c424b5a66c1526af49e67c97eaea7833a30d4fffe0df1",
    "feature_audit_sha256": "5d40f792e2d2dbf90cae20f4acfd02fe08123f63a6b2a35d223cfb0dc10a0f7d",
    "plan_replayed_from_locked_source": true,
    "capital_formula_verified": true,
    "target_outcome_used": false,
    "same_day_shock_selection_equal": true,
    "disclaimer": "Backtest là số liệu lịch sử, không bảo đảm kết quả tương lai."
  },
  "automation": {
    "pipeline_version": "MB_FUSION4_180_DAILY_TXN_V1",
    "schedule": "19:15 Asia/Bangkok",
    "retry_schedule": "19:30, 19:45 Asia/Bangkok",
    "status": "SHEETS_APPLIED_READBACK_VERIFIED_READY_TO_PUBLISH",
    "source_sheet_status": "VERIFIED_27_OF_27",
    "personal_ledger_policy": "ONLY_SETTLE_EXISTING_ACTUAL_ORDERS",
    "five_person_review_status": "READBACK_VERIFIED_NO_INFERRED_PNL",
    "sheets_payload_hash": "b507eb5ecf2236494a4c5c11017169ed0bc0be909da99b385ee72c679973d3e2"
  }
}
