{
  "schema_version": "MB_CHAMPION_STATE_V4",
  "project": "MB CHAMPION",
  "champion": "R39 DAILY MASTER",
  "config_id": "MB_CHAMPION_R39_DAILY_MASTER_V01_20260722",
  "champion_settled_through": "2026-07-23",
  "actual_settled_through": "2026-07-24",
  "planned_through": "2026-07-24",
  "latest_champion_settlement": "data/mb-champion-settlements/2026-07-23.json",
  "latest_actual_order": "data/mb-champion-actual-orders/2026-07-24.json",
  "latest_actual_settlement": "data/mb-champion-actual-settlements/2026-07-24.json",
  "latest_transaction": "data/mb-champion-transactions/2026-07-24.json",
  "latest_codes": ["13", "55", "83", "28"],
  "points_by_code": {"13": 50, "55": 50, "83": 25, "28": 25},
  "hits_by_code": {"13": 1, "55": 0, "83": 0, "28": 0},
  "total_points": 150,
  "capital_vnd": 3450000,
  "return_vnd": 4000000,
  "daily_net_profit_vnd": 550000,
  "actual_cumulative_net_profit_vnd": 15706000,
  "actual_sheet_row": "Linh!A16:H16",
  "status": "REAL_ORDER_SETTLED_WIN",
  "next_session_status": "NOT_YET_LOCKED",
  "updated_at": "2026-07-24T18:34:00+07:00"
}